README.rst
setup.py
django_localflavor_us/__init__.py
django_localflavor_us/forms.py
django_localflavor_us/models.py
django_localflavor_us/us_states.py
django_localflavor_us.egg-info/PKG-INFO
django_localflavor_us.egg-info/SOURCES.txt
django_localflavor_us.egg-info/dependency_links.txt
django_localflavor_us.egg-info/requires.txt
django_localflavor_us.egg-info/top_level.txt