Metadata-Version: 1.1
Name: django-localflavor-us
Version: 1.1
Summary: Country-specific Django helpers for U.S.A.
Home-page: https://github.com/django/django-localflavor-us
Author: Django Software Foundation
Author-email: foundation@djangoproject.com
License: BSD
Platform: UNKNOWN
Classifier: Development Status :: 5 - Production/Stable
Classifier: Environment :: Web Environment
Classifier: Framework :: Django
Classifier: Intended Audience :: Developers
Classifier: License :: OSI Approved :: BSD License
Classifier: Operating System :: OS Independent
Classifier: Programming Language :: Python
